bunnymq.py
bunnymq-0.0.15.dist-info/LICENSE
bunnymq-0.0.15.dist-info/WHEEL
bunnymq-0.0.15.dist-info/METADATA
bunnymq-0.0.15.dist-info/RECORD
