Metadata-Version: 2.1
Name: bunnymq
Version: 0.0.15
Summary: Simple messaging with RabbitMQ and Python.
Home-page: https://github.com/havefish/bunnymq
License: UNKNOWN
Author: havefish
Author-email: havefish@protonmail.com
Classifier: Intended Audience :: Developers
Classifier: License :: OSI Approved :: MIT License
Classifier: Programming Language :: Python :: 3.6
Classifier: Programming Language :: Python :: 3.7
Classifier: Programming Language :: Python :: 3.8
Classifier: Topic :: Software Development :: Libraries :: Python Modules
Requires-Dist: pika
